textsearch/__init__.py
textsearch-0.0.24.dist-info/METADATA
textsearch-0.0.24.dist-info/WHEEL
textsearch-0.0.24.dist-info/top_level.txt
textsearch-0.0.24.dist-info/RECORD
